timeextras
