Metadata-Version: 1.0
Name: timeextras
Version: 1.0
Summary: Time related extra functionalities
Home-page: https://github.com/sharonlev/pyTimeExtras
Author: Sharon Lev
Author-email: sharon_lev@yahoo.com
License:                     GNU GENERAL PUBLIC LICENSE
